simple_talk/__init__.py
simple_talk/helpers.py
simple_talk-0.1.10.dist-info/METADATA
simple_talk-0.1.10.dist-info/WHEEL
simple_talk-0.1.10.dist-info/licenses/LICENSE
simple_talk-0.1.10.dist-info/RECORD
