Metadata-Version: 2.4
Name: simple-talk
Version: 0.1.10
Project-URL: Repository, https://github.com/chuanconggao/SimpleTalk/
Author-email: Chuancong Gao <chuanconggao@users.noreply.github.com>
License-File: LICENSE
Requires-Python: >=3.12
Requires-Dist: extratools-av>=0.1.0
Requires-Dist: extratools-core>=0.1.24
Requires-Dist: extratools-text>=0.1.1
Requires-Dist: moviepy>=2.2.1
Requires-Dist: textstat>=0.7.7
Provides-Extra: polly
Requires-Dist: boto3>=1.37.19; extra == 'polly'
Provides-Extra: spacy-models
Requires-Dist: en-core-web-trf; extra == 'spacy-models'
